{"trial_id": "0038", "hyperparameters": {"space": [{"class_name": "Int", "config": {"name": "num_layers", "default": null, "conditions": [], "min_value": 1, "max_value": 2, "step": 1, "sampling": "linear"}}, {"class_name": "Int", "config": {"name": "units_0", "default": null, "conditions": [], "min_value": 8, "max_value": 48, "step": 8, "sampling": "linear"}}, {"class_name": "Float", "config": {"name": "recurrent_dropout_rate", "default": 0.1, "conditions": [], "min_value": 0.1, "max_value": 0.5, "step": 0.1, "sampling": "linear"}}, {"class_name": "Boolean", "config": {"name": "dropout", "default": false, "conditions": []}}, {"class_name": "Int", "config": {"name": "units_1", "default": null, "conditions": [], "min_value": 8, "max_value": 48, "step": 8, "sampling": "linear"}}, {"class_name": "Float", "config": {"name": "dropout_rate", "default": 0.1, "conditions": [], "min_value": 0.1, "max_value": 0.5, "step": 0.1, "sampling": "linear"}}], "values": {"num_layers": 1, "units_0": 48, "recurrent_dropout_rate": 0.30000000000000004, "dropout": false, "units_1": 40, "dropout_rate": 0.1, "tuner/epochs": 6, "tuner/initial_epoch": 2, "tuner/bracket": 3, "tuner/round": 1, "tuner/trial_id": "0033"}}, "metrics": {"metrics": {"loss": {"direction": "min", "observations": [{"value": [0.811163604259491], "step": 1}]}, "mean_absolute_error": {"direction": "min", "observations": [{"value": [0.7034260630607605], "step": 1}]}, "val_loss": {"direction": "min", "observations": [{"value": [6.616852283477783], "step": 1}]}, "val_mean_absolute_error": {"direction": "min", "observations": [{"value": [2.0742604732513428], "step": 1}]}}}, "score": 2.0742604732513428, "best_step": 1, "status": "COMPLETED", "message": null}